Metadata-Version: 1.1
Name: corsemall
Version: 0.2.0
Summary: Serves JSON data with CORS allowed from *.json files at given path.
Home-page: https://github.com/hvnsweeting/corsemall
Author: Viet Hung Nguyen
Author-email: hvn@familug.org
License: MIT
Platform: UNKNOWN
Classifier: Environment :: Console
Classifier: Topic :: Terminals :: Terminal Emulators/X Terminals
